torchmb/__init__.py
torchmb/base.py
torchmb/batch.py
torchmb/functional.py
torchmb/layers.py
torchmb/types.py
torchmb-0.2.dist-info/METADATA
torchmb-0.2.dist-info/WHEEL
torchmb-0.2.dist-info/top_level.txt
torchmb-0.2.dist-info/RECORD
