Metadata-Version: 2.1
Name: torchmb
Version: 0.2
Summary: PyTorch Model Batcher.
Author: admk
Project-URL: Homepage, https://github.com/admk/torchmb
Project-URL: Issues, https://github.com/admk/torchmb/issues
Classifier: Programming Language :: Python :: 3
Classifier: License :: OSI Approved :: MIT License
Classifier: Operating System :: OS Independent
Requires-Python: >=3.10
Requires-Dist: torch
Requires-Dist: einops
